{"id":"gitopia","symbol":"lore","name":"Gitopia","web_slug":"gitopia","asset_platform_id":null,"platforms":{"":""},"detail_platforms":{"":{"decimal_place":null,"contract_address":""}},"block_time_in_minutes":0,"hashing_algorithm":null,"categories":["Infrastructure"],"preview_listing":false,"public_notice":null,"additional_notices":["Kindly be aware of \u003ca href='https://www.coingecko.com/en/glossary/rug-pulled' target='_blank'\u003eliquidity-related risks\u003c/a\u003e. This notice is not directed at any project in particular, and is more of a cautionary reminder."],"localization":{"en":"Gitopia","de":"","es":"","fr":"","it":"","pl":"","ro":"","hu":"","nl":"","pt":"","sv":"","vi":"","tr":"","ru":"","ja":"","zh":"","zh-tw":"","ko":"","ar":"","th":"","id":"","cs":"","da":"","el":"","hi":"","no":"","sk":"","uk":"","he":"","fi":"","bg":"","hr":"","lt":"","sl":""},"description":{"en":"What is the project about?\r\n\r\n\r\nWhat makes your project unique?\r\n\r\n\r\nHistory of your project.\r\n\r\n\r\nWhat’s next for your project?\r\n\r\n\r\nWhat can your token be used for?\r\n\r\n","de":"","es":"","fr":"","it":"","pl":"","ro":"","hu":"","nl":"","pt":"","sv":"","vi":"","tr":"","ru":"","ja":"","zh":"","zh-tw":"","ko":"","ar":"","th":"","id":"","cs":"","da":"","el":"","hi":"","no":"","sk":"","uk":"","he":"","fi":"","bg":"","hr":"","lt":"","sl":""},"links":{"homepage":["https://gitopia.com","https://docs.gitopia.com","https://blog.gitopia.com"],"whitepaper":"https://gitopia.com/whitepaper.pdf","blockchain_site":["https://explorer.gitopia.com","","","","","","","","",""],"official_forum_url":["","",""],"chat_url":["https://discord.gg/Jd2ATcs","",""],"announcement_url":["",""],"twitter_screen_name":"gitopiaDAO","facebook_username":"","bitcointalk_thread_identifier":null,"telegram_channel_identifier":"Gitopia","subreddit_url":"https://www.reddit.com","repos_url":{"github":["https://github.com/gitopia"],"bitbucket":[]}},"image":{"thumb":"https://coin-images.coingecko.com/coins/images/30392/thumb/0r9YJOJW_400x400.png?1696529281","small":"https://coin-images.coingecko.com/coins/images/30392/small/0r9YJOJW_400x400.png?1696529281","large":"https://coin-images.coingecko.com/coins/images/30392/large/0r9YJOJW_400x400.png?1696529281"},"country_origin":"","genesis_date":null,"sentiment_votes_up_percentage":null,"sentiment_votes_down_percentage":null,"watchlist_portfolio_users":542,"market_cap_rank":null,"market_data":{"current_price":{"aed":0.02995003,"ars":7.87,"aud":0.01179874,"bch":2.322e-05,"bdt":0.974213,"bhd":0.00306997,"bmd":0.0081541,"bnb":1.364e-05,"brl":0.04430859,"btc":1.23902e-07,"cad":0.0110272,"chf":0.00685943,"clp":7.33,"cny":0.057174,"czk":0.183577,"dkk":0.054463,"dot":0.00169552,"eos":0.01508176,"eth":3.06e-06,"eur":0.00729902,"gbp":0.00609835,"gel":0.02217916,"hkd":0.063377,"huf":2.9,"idr":123.33,"ils":0.03015575,"inr":0.682633,"jpy":1.16,"krw":10.68,"kwd":0.00248444,"lkr":2.43,"ltc":0.0001168,"mmk":17.11,"mxn":0.160707,"myr":0.03363568,"ngn":13.61,"nok":0.085642,"nzd":0.01285934,"php":0.456703,"pkr":2.26,"pln":0.0312347,"rub":0.768315,"sar":0.03058739,"sek":0.082275,"sgd":0.01043644,"thb":0.263831,"try":0.278335,"twd":0.257588,"uah":0.335622,"usd":0.0081541,"vef":0.00081647,"vnd":200.67,"xag":0.00025777,"xau":3.07e-06,"xdr":0.00603113,"xlm":0.07974981,"xrp":0.0124911,"yfi":1.46e-06,"zar":0.139567,"bits":0.123902,"link":0.00064684,"sats":12.39},"total_value_locked":null,"mcap_to_tvl_ratio":null,"fdv_to_tvl_ratio":null,"roi":null,"ath":{"aed":0.259708,"ars":47.52,"aud":0.105466,"bch":0.00063627,"bdt":7.62,"bhd":0.02665772,"bmd":0.070707,"bnb":0.00027273,"brl":0.348149,"btc":2.67e-06,"cad":0.09451,"chf":0.063588,"clp":55.68,"cny":0.503394,"czk":1.55,"dkk":0.48868,"dot":0.01414088,"eos":0.10014762,"eth":3.854e-05,"eur":0.065594,"gbp":0.056323,"gel":0.141948,"hkd":0.554115,"huf":24.23,"idr":1049.81,"ils":0.25836,"inr":5.83,"jpy":9.85,"krw":91.62,"kwd":0.02174151,"lkr":20.79,"ltc":0.00080873,"mmk":147.77,"mxn":1.23,"myr":0.326031,"ngn":72.84,"nok":0.771451,"nzd":0.116085,"php":3.96,"pkr":20.3,"pln":0.29341,"rub":5.8,"sar":0.265192,"sek":0.763898,"sgd":0.094974,"thb":2.45,"try":1.7,"twd":2.17,"uah":2.6,"usd":0.070707,"vef":0.00707992,"vnd":1660.77,"xag":0.00290616,"xau":3.599e-05,"xdr":0.052895,"xlm":0.81531052,"xrp":0.13434611,"yfi":1.201e-05,"zar":1.34,"bits":2.67,"link":0.01188165,"sats":267.18},"ath_change_percentage":{"aed":-88.47294,"ars":-83.44017,"aud":-88.81773,"bch":-96.3526,"bdt":-87.21653,"bhd":-88.48887,"bmd":-88.47294,"bnb":-95.00016,"brl":-87.27875,"btc":-95.36705,"cad":-88.33737,"chf":-89.21753,"clp":-86.83702,"cny":-88.64732,"czk":-88.18111,"dkk":-88.86007,"dot":-88.027,"eos":-84.96339,"eth":-92.06626,"eur":-88.87731,"gbp":-89.17743,"gel":-84.38213,"hkd":-88.56765,"huf":-88.04789,"idr":-88.25737,"ils":-88.33319,"inr":-88.30143,"jpy":-88.23281,"krw":-88.3436,"kwd":-88.57791,"lkr":-88.29826,"ltc":-85.57988,"mmk":-88.42787,"mxn":-86.93273,"myr":-89.6879,"ngn":-81.33011,"nok":-88.90355,"nzd":-88.92741,"php":-88.47531,"pkr":-88.85229,"pln":-89.35931,"rub":-86.76008,"sar":-88.47106,"sek":-89.23439,"sgd":-89.01617,"thb":-89.23605,"try":-83.67047,"twd":-88.1522,"uah":-87.08902,"usd":-88.47294,"vef":-88.47294,"vnd":-87.92229,"xag":-91.1341,"xau":-91.48208,"xdr":-88.60292,"xlm":-90.22442,"xrp":-90.70785,"yfi":-87.81282,"zar":-89.55767,"bits":-95.36705,"link":-94.57386,"sats":-95.36705},"ath_date":{"aed":"2023-06-09T03:16:31.960Z","ars":"2024-07-09T14:15:45.762Z","aud":"2023-06-09T03:16:31.960Z","bch":"2023-06-09T03:16:31.960Z","bdt":"2023-06-09T03:16:31.960Z","bhd":"2023-06-09T03:16:31.960Z","bmd":"2023-06-09T03:16:31.960Z","bnb":"2023-06-09T03:16:31.960Z","brl":"2023-06-09T03:16:31.960Z","btc":"2023-06-09T03:16:31.960Z","cad":"2023-06-09T03:16:31.960Z","chf":"2023-06-09T03:16:31.960Z","clp":"2023-06-09T03:16:31.960Z","cny":"2023-06-09T03:16:31.960Z","czk":"2023-06-09T03:16:31.960Z","dkk":"2023-06-09T03:16:31.960Z","dot":"2023-06-09T03:16:31.960Z","eos":"2024-07-09T14:10:28.207Z","eth":"2023-06-09T03:16:31.960Z","eur":"2023-06-09T03:16:31.960Z","gbp":"2023-06-09T03:16:31.960Z","gel":"2024-07-09T14:15:45.762Z","hkd":"2023-06-09T03:16:31.960Z","huf":"2023-06-09T03:16:31.960Z","idr":"2023-06-09T03:16:31.960Z","ils":"2023-06-09T03:16:31.960Z","inr":"2023-06-09T03:16:31.960Z","jpy":"2023-06-09T03:16:31.960Z","krw":"2023-06-09T03:16:31.960Z","kwd":"2023-06-09T03:16:31.960Z","lkr":"2023-06-09T03:16:31.960Z","ltc":"2023-06-09T03:16:31.960Z","mmk":"2023-06-09T03:16:31.960Z","mxn":"2023-06-09T03:16:31.960Z","myr":"2023-06-09T03:16:31.960Z","ngn":"2024-07-09T14:15:45.762Z","nok":"2023-06-09T03:16:31.960Z","nzd":"2023-06-09T03:16:31.960Z","php":"2023-06-09T03:16:31.960Z","pkr":"2023-06-09T03:16:31.960Z","pln":"2023-06-09T03:16:31.960Z","rub":"2023-06-09T03:16:31.960Z","sar":"2023-06-09T03:16:31.960Z","sek":"2023-06-09T03:16:31.960Z","sgd":"2023-06-09T03:16:31.960Z","thb":"2023-06-09T03:16:31.960Z","try":"2024-07-09T14:15:45.762Z","twd":"2023-06-09T03:16:31.960Z","uah":"2023-06-09T03:16:31.960Z","usd":"2023-06-09T03:16:31.960Z","vef":"2023-06-09T03:16:31.960Z","vnd":"2023-06-09T03:16:31.960Z","xag":"2023-06-09T03:16:31.960Z","xau":"2023-06-09T03:16:31.960Z","xdr":"2023-06-09T03:16:31.960Z","xlm":"2023-06-09T03:16:31.960Z","xrp":"2023-06-09T03:16:31.960Z","yfi":"2023-06-09T03:16:31.960Z","zar":"2023-06-09T03:16:31.960Z","bits":"2023-06-09T03:16:31.960Z","link":"2023-06-09T03:16:31.960Z","sats":"2023-06-09T03:16:31.960Z"},"atl":{"aed":0.01651592,"ars":3.99,"aud":0.00695268,"bch":1.475e-05,"bdt":0.528038,"bhd":0.00169494,"bmd":0.00449657,"bnb":9.51e-06,"brl":0.0259827,"btc":8.46e-08,"cad":0.00622456,"chf":0.00379899,"clp":4.3,"cny":0.03194097,"czk":0.10339,"dkk":0.03050697,"dot":0.00113936,"eos":0.01007445,"eth":1.91e-06,"eur":0.00408886,"gbp":0.0035183,"gel":0.01216323,"hkd":0.0349816,"huf":1.63,"idr":72.83,"ils":0.01720725,"inr":0.378412,"jpy":0.639951,"krw":6.13,"kwd":0.00137225,"lkr":1.35,"ltc":7.488e-05,"mmk":9.43,"mxn":0.088359,"myr":0.01989734,"ngn":7.17,"nok":0.04954191,"nzd":0.00756307,"php":0.259859,"pkr":1.25,"pln":0.01762864,"rub":0.382095,"sar":0.01687913,"sek":0.04721274,"sgd":0.00593423,"thb":0.158482,"try":0.150194,"twd":0.146883,"uah":0.185083,"usd":0.00449657,"vef":0.00045024,"vnd":112.85,"xag":0.00016657,"xau":1.88e-06,"xdr":0.00338233,"xlm":0.05258989,"xrp":0.00874912,"yfi":1.0e-06,"zar":0.083617,"bits":0.0846,"link":0.00047725,"sats":8.46},"atl_change_percentage":{"aed":81.25963,"ars":97.29239,"aud":69.62511,"bch":57.28522,"bdt":84.41454,"bhd":81.04468,"bmd":81.25963,"bnb":43.33941,"brl":70.45519,"btc":46.31357,"cad":77.07739,"chf":80.47912,"clp":70.36669,"cny":78.91969,"czk":77.47958,"dkk":78.44662,"dot":48.59966,"eos":49.47533,"eth":59.706,"eur":78.43068,"gbp":73.2551,"gel":82.26476,"hkd":81.09047,"huf":77.54138,"idr":69.27305,"ils":75.17227,"inr":80.31386,"jpy":81.05131,"krw":74.09941,"kwd":80.968,"lkr":80.1565,"ltc":55.74645,"mmk":81.25963,"mxn":81.79854,"myr":68.97084,"ngn":89.66353,"nok":72.7903,"nzd":69.95241,"php":75.67196,"pkr":80.74105,"pln":77.10266,"rub":100.99012,"sar":81.13355,"sek":74.18665,"sgd":75.79007,"thb":66.39962,"try":85.23466,"twd":75.29172,"uah":81.2553,"usd":81.25963,"vef":81.25963,"vnd":77.74048,"xag":54.68694,"xau":62.66147,"xdr":78.23326,"xlm":51.55256,"xrp":42.68449,"yfi":46.14602,"zar":66.83709,"bits":46.31357,"link":35.09005,"sats":46.31357},"atl_date":{"aed":"2024-08-05T13:31:32.831Z","ars":"2023-10-19T16:59:01.871Z","aud":"2024-08-05T13:31:32.831Z","bch":"2024-08-17T14:36:05.362Z","bdt":"2024-08-05T13:31:32.831Z","bhd":"2024-08-05T13:31:32.831Z","bmd":"2024-08-05T13:31:32.831Z","bnb":"2024-08-17T20:06:03.894Z","brl":"2024-08-05T13:31:32.831Z","btc":"2024-08-16T18:01:29.959Z","cad":"2024-08-05T13:31:32.831Z","chf":"2024-08-05T13:31:32.831Z","clp":"2024-08-05T13:31:32.831Z","cny":"2024-08-05T13:31:32.831Z","czk":"2024-08-05T13:31:32.831Z","dkk":"2024-08-05T13:31:32.831Z","dot":"2024-08-08T08:19:57.070Z","eos":"2024-08-17T06:10:52.405Z","eth":"2024-08-16T16:31:12.170Z","eur":"2024-08-05T13:31:32.831Z","gbp":"2024-08-05T13:31:32.831Z","gel":"2024-08-05T13:31:32.831Z","hkd":"2024-08-05T13:31:32.831Z","huf":"2024-08-05T13:31:32.831Z","idr":"2024-08-05T13:31:32.831Z","ils":"2024-08-05T13:31:32.831Z","inr":"2024-08-05T13:31:32.831Z","jpy":"2024-08-05T13:31:32.831Z","krw":"2024-08-05T13:31:32.831Z","kwd":"2024-08-05T13:31:32.831Z","lkr":"2024-08-05T13:31:32.831Z","ltc":"2024-08-16T16:25:59.769Z","mmk":"2024-08-05T13:31:32.831Z","mxn":"2024-08-05T13:31:32.831Z","myr":"2024-08-05T13:31:32.831Z","ngn":"2024-08-05T13:31:32.831Z","nok":"2024-08-05T13:31:32.831Z","nzd":"2024-08-05T13:31:32.831Z","php":"2024-08-05T13:31:32.831Z","pkr":"2024-08-05T13:31:32.831Z","pln":"2024-08-05T13:31:32.831Z","rub":"2024-08-05T13:31:32.831Z","sar":"2024-08-05T13:31:32.831Z","sek":"2024-08-05T13:31:32.831Z","sgd":"2024-08-05T13:31:32.831Z","thb":"2024-08-05T13:31:32.831Z","try":"2024-08-05T13:31:32.831Z","twd":"2024-08-05T13:31:32.831Z","uah":"2024-08-05T13:31:32.831Z","usd":"2024-08-05T13:31:32.831Z","vef":"2024-08-05T13:31:32.831Z","vnd":"2024-08-05T13:31:32.831Z","xag":"2024-08-05T13:31:32.831Z","xau":"2024-08-05T13:31:32.831Z","xdr":"2024-08-05T13:31:32.831Z","xlm":"2024-08-08T09:50:54.448Z","xrp":"2024-08-08T09:50:54.448Z","yfi":"2024-08-05T18:36:15.795Z","zar":"2024-08-05T13:31:32.831Z","bits":"2024-08-16T18:01:29.959Z","link":"2024-09-09T10:18:39.264Z","sats":"2024-08-16T18:01:29.959Z"},"market_cap":{"aed":0.0,"ars":0.0,"aud":0.0,"bch":0.0,"bdt":0.0,"bhd":0.0,"bmd":0.0,"bnb":0.0,"brl":0.0,"btc":0.0,"cad":0.0,"chf":0.0,"clp":0.0,"cny":0.0,"czk":0.0,"dkk":0.0,"dot":0.0,"eos":0.0,"eth":0.0,"eur":0.0,"gbp":0.0,"gel":0.0,"hkd":0.0,"huf":0.0,"idr":0.0,"ils":0.0,"inr":0.0,"jpy":0.0,"krw":0.0,"kwd":0.0,"lkr":0.0,"ltc":0.0,"mmk":0.0,"mxn":0.0,"myr":0.0,"ngn":0.0,"nok":0.0,"nzd":0.0,"php":0.0,"pkr":0.0,"pln":0.0,"rub":0.0,"sar":0.0,"sek":0.0,"sgd":0.0,"thb":0.0,"try":0.0,"twd":0.0,"uah":0.0,"usd":0.0,"vef":0.0,"vnd":0.0,"xag":0.0,"xau":0.0,"xdr":0.0,"xlm":0.0,"xrp":0.0,"yfi":0.0,"zar":0.0,"bits":0.0,"link":0.0,"sats":0.0},"market_cap_rank":null,"fully_diluted_valuation":{"aed":14975679,"ars":3936439026,"aud":5899631,"bch":11610,"bdt":487128156,"bhd":1535054,"bmd":4077234,"bnb":6824,"brl":22155280,"btc":61.949,"cad":5513847,"chf":3429867,"clp":3666044645,"cny":28588339,"czk":91792800,"dkk":27232659,"dot":847612,"eos":7540452,"eth":1531,"eur":3649675,"gbp":3049310,"gel":11090076,"hkd":31689687,"huf":1448848634,"idr":61667547508,"ils":15078548,"inr":341331935,"jpy":579603266,"krw":5342378877,"kwd":1242276,"lkr":1217235709,"ltc":58394,"mmk":8554036217,"mxn":80356975,"myr":16818589,"ngn":6802823588,"nok":42822777,"nzd":6429956,"php":228361764,"pkr":1132247787,"pln":15618043,"rub":384174593,"sar":15294376,"sek":41139288,"sgd":5218451,"thb":131921125,"try":139173521,"twd":128799815,"uah":167818579,"usd":4077234,"vef":408253,"vnd":100340720349,"xag":128892,"xau":1533.73,"xdr":3015697,"xlm":39880469,"xrp":6246776,"yfi":732.07,"zar":69786584,"bits":61949300,"link":323246,"sats":6194930038},"market_cap_fdv_ratio":null,"total_volume":{"aed":2238.25,"ars":588337,"aud":881.75,"bch":1.735461,"bdt":72806,"bhd":229.43,"bmd":609.38,"bnb":1.019179,"brl":3311.31,"btc":0.00925957,"cad":824.09,"chf":512.62,"clp":547924,"cny":4272.79,"czk":13719.27,"dkk":4070.17,"dot":126.711,"eos":1127,"eth":0.22878749,"eur":545.48,"gbp":455.75,"gel":1657.51,"hkd":4736.31,"huf":216544,"idr":9216778,"ils":2253.63,"inr":51015,"jpy":86627,"krw":798467,"kwd":185.67,"lkr":181927,"ltc":8.728598,"mmk":1278479,"mxn":12010.08,"myr":2513.69,"ngn":1016744,"nok":6400.26,"nzd":961.02,"php":34131,"pkr":169225,"pln":2334.26,"rub":57418,"sar":2285.88,"sek":6148.64,"sgd":779.95,"thb":19716.82,"try":20801,"twd":19250.31,"uah":25082,"usd":609.38,"vef":61.02,"vnd":14996837,"xag":19.26,"xau":0.22923,"xdr":450.72,"xlm":5960,"xrp":933.496,"yfi":0.10940923,"zar":10430.24,"bits":9259.57,"link":48.340446,"sats":925957},"high_24h":{"aed":0.02996346,"ars":7.88,"aud":0.01180403,"bch":2.327e-05,"bdt":0.97465,"bhd":0.00307135,"bmd":0.00815776,"bnb":1.366e-05,"brl":0.04432846,"btc":1.23993e-07,"cad":0.01103215,"chf":0.00686251,"clp":7.34,"cny":0.0572,"czk":0.18366,"dkk":0.054487,"dot":0.00169662,"eos":0.01509288,"eth":3.06e-06,"eur":0.0073023,"gbp":0.00610108,"gel":0.02218911,"hkd":0.063405,"huf":2.9,"idr":123.38,"ils":0.03016928,"inr":0.68294,"jpy":1.16,"krw":10.69,"kwd":0.00248556,"lkr":2.44,"ltc":0.00011696,"mmk":17.11,"mxn":0.160779,"myr":0.03365077,"ngn":13.61,"nok":0.08568,"nzd":0.01286511,"php":0.456908,"pkr":2.27,"pln":0.03124871,"rub":0.76866,"sar":0.03060111,"sek":0.082312,"sgd":0.01044112,"thb":0.263949,"try":0.27846,"twd":0.257704,"uah":0.335773,"usd":0.00815776,"vef":0.00081684,"vnd":200.76,"xag":0.00025789,"xau":3.07e-06,"xdr":0.00603383,"xlm":0.08016294,"xrp":0.01300523,"yfi":1.49e-06,"zar":0.13963,"bits":0.123993,"link":0.0006458,"sats":12.4},"low_24h":{"aed":0.02778339,"ars":7.3,"aud":0.0109452,"bch":2.154e-05,"bdt":0.903737,"bhd":0.00284788,"bmd":0.00756422,"bnb":1.264e-05,"brl":0.04110324,"btc":1.15284e-07,"cad":0.01022948,"chf":0.00636321,"clp":6.8,"cny":0.053038,"czk":0.170297,"dkk":0.050523,"dot":0.00158447,"eos":0.01422191,"eth":2.83e-06,"eur":0.006771,"gbp":0.00565718,"gel":0.02057469,"hkd":0.058792,"huf":2.69,"idr":114.41,"ils":0.02797424,"inr":0.633251,"jpy":1.075,"krw":9.91,"kwd":0.00230716,"lkr":2.26,"ltc":0.00010879,"mmk":15.87,"mxn":0.149081,"myr":0.03120242,"ngn":12.62,"nok":0.079446,"nzd":0.01192908,"php":0.423665,"pkr":2.1,"pln":0.02897513,"rub":0.712734,"sar":0.02837465,"sek":0.076323,"sgd":0.00968145,"thb":0.244745,"try":0.258411,"twd":0.238954,"uah":0.311343,"usd":0.00756422,"vef":0.00075741,"vnd":186.16,"xag":0.00023912,"xau":2.85e-06,"xdr":0.00559483,"xlm":0.07578259,"xrp":0.01206291,"yfi":1.41e-06,"zar":0.12947,"bits":0.115284,"link":0.00058919,"sats":11.53},"price_change_24h":0.00050518,"price_change_percentage_24h":6.60463,"price_change_percentage_7d":21.04359,"price_change_percentage_14d":32.7965,"price_change_percentage_30d":35.53162,"price_change_percentage_60d":9.25916,"price_change_percentage_200d":-76.22666,"price_change_percentage_1y":-53.68529,"market_cap_change_24h":0.0,"market_cap_change_percentage_24h":0.0,"price_change_24h_in_currency":{"aed":0.00185554,"ars":0.487738,"aud":0.00073098,"bch":1.51e-06,"bdt":0.060357,"bhd":0.0001902,"bmd":0.00050518,"bnb":9.16549e-07,"brl":0.00274511,"btc":7.557e-09,"cad":0.00068318,"chf":0.00042497,"clp":0.454235,"cny":0.00354219,"czk":0.01137343,"dkk":0.00337422,"dot":0.00010582,"eos":0.00084006,"eth":2.06003e-07,"eur":0.00045221,"gbp":0.00037782,"gel":0.0013741,"hkd":0.00392646,"huf":0.179517,"idr":7.64,"ils":0.00186828,"inr":0.04229216,"jpy":0.071815,"krw":0.661938,"kwd":0.00015144,"lkr":0.15082,"ltc":7.21e-06,"mmk":1.06,"mxn":0.0099565,"myr":0.00208388,"ngn":0.842892,"nok":0.00530588,"nzd":0.00079669,"php":0.02829478,"pkr":0.140289,"pln":0.00193513,"rub":0.04760051,"sar":0.00189502,"sek":0.00509729,"sgd":0.00064658,"thb":0.01634546,"try":0.0170299,"twd":0.01595872,"uah":0.02079328,"usd":0.00050518,"vef":5.058e-05,"vnd":12.43,"xag":1.597e-05,"xau":1.90035e-07,"xdr":0.00037365,"xlm":0.00382433,"xrp":0.00025178,"yfi":4.2347e-08,"zar":0.00864679,"bits":0.00755735,"link":5.415e-05,"sats":0.755735},"price_change_percentage_1h_in_currency":{"aed":0.33701,"ars":0.33701,"aud":0.33701,"bch":0.46091,"bdt":0.33701,"bhd":0.33701,"bmd":0.33701,"bnb":0.38501,"brl":0.33701,"btc":0.39086,"cad":0.33701,"chf":0.33701,"clp":0.33701,"cny":0.33701,"czk":0.33701,"dkk":0.33701,"dot":0.13281,"eos":0.15554,"eth":0.39652,"eur":0.33701,"gbp":0.33701,"gel":0.33701,"hkd":0.33701,"huf":0.33701,"idr":0.33701,"ils":0.33701,"inr":0.33701,"jpy":0.33701,"krw":0.33701,"kwd":0.33701,"lkr":0.33701,"ltc":0.29699,"mmk":0.33701,"mxn":0.33701,"myr":0.33701,"ngn":0.33701,"nok":0.33701,"nzd":0.33701,"php":0.33701,"pkr":0.33701,"pln":0.33701,"rub":0.33701,"sar":0.33701,"sek":0.33701,"sgd":0.33701,"thb":0.33701,"try":0.33701,"twd":0.33701,"uah":0.33701,"usd":0.33701,"vef":0.33701,"vnd":0.33701,"xag":0.33701,"xau":0.33701,"xdr":0.33701,"xlm":-0.00666,"xrp":0.25575,"yfi":0.28971,"zar":0.33701,"bits":0.39086,"link":0.71156,"sats":0.39086},"price_change_percentage_24h_in_currency":{"aed":6.60463,"ars":6.60463,"aud":6.60463,"bch":6.93979,"bdt":6.60463,"bhd":6.60463,"bmd":6.60463,"bnb":7.20497,"brl":6.60463,"btc":6.49564,"cad":6.60463,"chf":6.60463,"clp":6.60463,"cny":6.60463,"czk":6.60463,"dkk":6.60463,"dot":6.65657,"eos":5.89861,"eth":7.21451,"eur":6.60463,"gbp":6.60463,"gel":6.60463,"hkd":6.60463,"huf":6.60463,"idr":6.60463,"ils":6.60463,"inr":6.60463,"jpy":6.60463,"krw":6.60463,"kwd":6.49139,"lkr":6.60463,"ltc":6.57741,"mmk":6.60463,"mxn":6.60463,"myr":6.60463,"ngn":6.60463,"nok":6.60463,"nzd":6.60463,"php":6.60463,"pkr":6.60463,"pln":6.60463,"rub":6.60463,"sar":6.60463,"sek":6.60463,"sgd":6.60463,"thb":6.60462,"try":6.51726,"twd":6.60463,"uah":6.60463,"usd":6.60463,"vef":6.60463,"vnd":6.60463,"xag":6.60463,"xau":6.60463,"xdr":6.60463,"xlm":5.03696,"xrp":2.05713,"yfi":2.9787,"zar":6.60463,"bits":6.49564,"link":9.13575,"sats":6.49564},"price_change_percentage_7d_in_currency":{"aed":21.04359,"ars":21.57569,"aud":19.08194,"bch":17.8546,"bdt":21.20826,"bhd":21.12659,"bmd":21.04359,"bnb":18.09332,"brl":19.26144,"btc":15.91479,"cad":20.50892,"chf":19.79512,"clp":17.22959,"cny":20.35357,"czk":21.37839,"dkk":20.99286,"dot":9.44602,"eos":15.0249,"eth":17.38535,"eur":21.03277,"gbp":20.60447,"gel":20.6002,"hkd":20.74841,"huf":22.14035,"idr":20.75656,"ils":18.76859,"inr":21.37604,"jpy":19.63896,"krw":19.02739,"kwd":21.05511,"lkr":18.6289,"ltc":17.05278,"mmk":21.04359,"mxn":22.90633,"myr":18.74074,"ngn":23.39834,"nok":21.26469,"nzd":19.04879,"php":21.81787,"pkr":21.16797,"pln":21.2081,"rub":23.27928,"sar":21.00207,"sek":20.10323,"sgd":20.04005,"thb":18.71981,"try":21.10319,"twd":19.56371,"uah":20.72728,"usd":21.04359,"vef":21.04359,"vnd":21.07664,"xag":19.28134,"xau":19.40254,"xdr":20.99418,"xlm":13.8591,"xrp":9.7176,"yfi":7.91849,"zar":18.86029,"bits":15.91479,"link":6.89688,"sats":15.91479},"price_change_percentage_14d_in_currency":{"aed":32.7965,"ars":33.8257,"aud":28.81896,"bch":21.19407,"bdt":32.72443,"bhd":32.55462,"bmd":32.7965,"bnb":23.67995,"brl":29.66396,"btc":20.69051,"cad":32.08351,"chf":31.5548,"clp":28.27039,"cny":31.26513,"czk":31.74667,"dkk":31.64545,"dot":23.97325,"eos":20.75411,"eth":18.73131,"eur":31.73863,"gbp":30.33835,"gel":33.78018,"hkd":32.33848,"huf":32.37032,"idr":30.32483,"ils":32.39654,"inr":32.53552,"jpy":34.04211,"krw":30.90283,"kwd":32.56894,"lkr":31.55701,"ltc":21.92783,"mmk":32.7965,"mxn":36.20638,"myr":27.34757,"ngn":35.17762,"nok":30.80692,"nzd":28.83839,"php":32.96028,"pkr":32.53381,"pln":31.59919,"rub":38.04393,"sar":32.75166,"sek":30.87744,"sgd":30.89429,"thb":28.7302,"try":33.96447,"twd":31.28788,"uah":32.10395,"usd":32.7965,"vef":32.7965,"vnd":32.98563,"xag":29.10984,"xau":28.80069,"xdr":32.48626,"xlm":26.03166,"xrp":19.48735,"yfi":17.72849,"zar":28.02176,"bits":20.69051,"link":17.32332,"sats":20.69051},"price_change_percentage_30d_in_currency":{"aed":35.53531,"ars":37.55768,"aud":32.65468,"bch":24.74163,"bdt":35.50411,"bhd":35.37556,"bmd":35.53162,"bnb":20.62537,"brl":30.30401,"btc":21.19132,"cad":35.84633,"chf":34.11935,"clp":33.39527,"cny":34.01027,"czk":34.73704,"dkk":34.15376,"dot":19.03866,"eos":21.65053,"eth":26.76021,"eur":34.10641,"gbp":33.00381,"gel":36.78887,"hkd":35.09361,"huf":35.5753,"idr":31.97428,"ils":38.16796,"inr":35.28325,"jpy":31.87307,"krw":32.84137,"kwd":35.10769,"lkr":35.23881,"ltc":22.25599,"mmk":35.53162,"mxn":35.82879,"myr":29.39889,"ngn":42.22121,"nok":34.00028,"nzd":33.49121,"php":34.92095,"pkr":35.14752,"pln":33.98645,"rub":40.87435,"sar":35.46954,"sek":33.13975,"sgd":32.89683,"thb":28.74547,"try":35.76349,"twd":33.77003,"uah":35.84926,"usd":35.53162,"vef":35.53162,"vnd":34.08776,"xag":23.68071,"xau":27.62962,"xdr":34.93924,"xlm":22.69128,"xrp":15.98737,"yfi":24.51122,"zar":30.05966,"bits":21.19132,"link":17.42939,"sats":21.19132},"price_change_percentage_60d_in_currency":{"aed":9.25916,"ars":13.33412,"aud":3.19168,"bch":32.29236,"bdt":11.13331,"bhd":9.14465,"bmd":9.25916,"bnb":7.16451,"brl":5.01332,"btc":9.92677,"cad":6.98946,"chf":4.35325,"clp":4.1664,"cny":6.12021,"czk":4.63621,"dkk":5.73977,"dot":24.19352,"eos":19.88916,"eth":34.99839,"eur":5.75214,"gbp":4.87021,"gel":9.46037,"hkd":8.6901,"huf":6.51089,"idr":1.5585,"ils":7.45208,"inr":9.28454,"jpy":3.0258,"krw":4.25997,"kwd":8.92988,"lkr":7.86496,"ltc":11.23242,"mmk":9.25916,"mxn":15.98961,"myr":-1.90575,"ngn":9.74722,"nok":4.87572,"nzd":2.3609,"php":4.89545,"pkr":8.75006,"pln":5.49201,"rub":21.12054,"sar":9.24387,"sek":2.82858,"sgd":4.47981,"thb":-0.68995,"try":12.57531,"twd":5.45281,"uah":9.69782,"usd":9.25916,"vef":9.25916,"vnd":6.3715,"xag":-0.8972,"xau":-0.32493,"xdr":7.23108,"xlm":9.20448,"xrp":7.24554,"yfi":10.90025,"zar":2.561,"bits":9.92677,"link":12.41079,"sats":9.92677},"price_change_percentage_200d_in_currency":{"aed":-76.22601,"ars":-72.98931,"aud":-77.18596,"bch":-70.58976,"bdt":-74.11519,"bhd":-76.25038,"bmd":-76.22666,"bnb":-76.55917,"brl":-74.01236,"btc":-73.6657,"cad":-76.11912,"chf":-77.20421,"clp":-77.41357,"cny":-76.80846,"czk":-76.77456,"dkk":-76.66603,"dot":-46.27193,"eos":-48.31725,"eth":-64.48855,"eur":-76.68094,"gbp":-77.23041,"gel":-75.64464,"hkd":-76.38167,"huf":-76.60992,"idr":-76.88529,"ils":-75.83121,"inr":-75.97845,"jpy":-77.11047,"krw":-76.27263,"kwd":-76.41592,"lkr":-76.81331,"ltc":-67.32057,"mmk":-76.24508,"mxn":-71.89458,"myr":-79.03474,"ngn":-75.33404,"nok":-76.14366,"nzd":-76.88345,"php":-75.94644,"pkr":-76.35015,"pln":-76.70369,"rub":-75.47171,"sar":-76.2234,"sek":-76.50824,"sgd":-77.14624,"thb":-78.39388,"try":-74.71438,"twd":-76.13336,"uah":-74.75379,"usd":-76.22666,"vef":-76.22666,"vnd":-76.29329,"xag":-81.2504,"xau":-80.55191,"xdr":-76.50872,"xlm":-65.22354,"xrp":-75.05725,"yfi":-56.44067,"zar":-78.06295,"bits":-73.6657,"link":-61.65631,"sats":-73.6657},"price_change_percentage_1y_in_currency":{"aed":-53.68529,"ars":27.76804,"aud":-56.92675,"bch":-69.47301,"bdt":-49.86514,"bhd":-53.745,"bmd":-53.68529,"bnb":-83.33645,"brl":-49.80064,"btc":-81.11338,"cad":-53.82134,"chf":-57.45181,"clp":-53.31143,"cny":-55.48758,"czk":-54.77085,"dkk":-56.15552,"dot":-60.77276,"eos":-50.6537,"eth":-71.08741,"eur":-56.17876,"gbp":-57.78073,"gel":-53.08156,"hkd":-54.02922,"huf":-55.32274,"idr":-54.78835,"ils":-55.003,"inr":-53.37821,"jpy":-55.9532,"krw":-55.0336,"kwd":-54.34564,"lkr":-57.40342,"ltc":-56.27129,"mmk":-53.7782,"mxn":-47.56027,"myr":-59.42484,"ngn":-1.18207,"nok":-54.48207,"nzd":-56.2311,"php":-54.19682,"pkr":-55.30289,"pln":-59.42801,"rub":-55.47014,"sar":-53.6758,"sek":-57.19498,"sgd":-56.62372,"thb":-59.04516,"try":-42.33738,"twd":-54.59089,"uah":-48.4381,"usd":-53.68529,"vef":-53.68529,"vnd":-53.2909,"xag":-67.48249,"xau":-67.75338,"xdr":-55.12996,"xlm":-47.75813,"xrp":-62.06864,"yfi":-57.01241,"zar":-58.09058,"bits":-81.11338,"link":-71.38232,"sats":-81.11338},"market_cap_change_24h_in_currency":{"aed":0.0,"ars":0.0,"aud":0.0,"bch":0.0,"bdt":0.0,"bhd":0.0,"bmd":0.0,"bnb":0.0,"brl":0.0,"btc":0.0,"cad":0.0,"chf":0.0,"clp":0.0,"cny":0.0,"czk":0.0,"dkk":0.0,"dot":0.0,"eos":0.0,"eth":0.0,"eur":0.0,"gbp":0.0,"gel":0.0,"hkd":0.0,"huf":0.0,"idr":0.0,"ils":0.0,"inr":0.0,"jpy":0.0,"krw":0.0,"kwd":0.0,"lkr":0.0,"ltc":0.0,"mmk":0.0,"mxn":0.0,"myr":0.0,"ngn":0.0,"nok":0.0,"nzd":0.0,"php":0.0,"pkr":0.0,"pln":0.0,"rub":0.0,"sar":0.0,"sek":0.0,"sgd":0.0,"thb":0.0,"try":0.0,"twd":0.0,"uah":0.0,"usd":0.0,"vef":0.0,"vnd":0.0,"xag":0.0,"xau":0.0,"xdr":0.0,"xlm":0.0,"xrp":0.0,"yfi":0.0,"zar":0.0,"bits":0.0,"link":0.0,"sats":0.0},"market_cap_change_percentage_24h_in_currency":{"aed":0.0,"ars":0.0,"aud":0.0,"bch":0.0,"bdt":0.0,"bhd":0.0,"bmd":0.0,"bnb":0.0,"brl":0.0,"btc":0.0,"cad":0.0,"chf":0.0,"clp":0.0,"cny":0.0,"czk":0.0,"dkk":0.0,"dot":0.0,"eos":0.0,"eth":0.0,"eur":0.0,"gbp":0.0,"gel":0.0,"hkd":0.0,"huf":0.0,"idr":0.0,"ils":0.0,"inr":0.0,"jpy":0.0,"krw":0.0,"kwd":0.0,"lkr":0.0,"ltc":0.0,"mmk":0.0,"mxn":0.0,"myr":0.0,"ngn":0.0,"nok":0.0,"nzd":0.0,"php":0.0,"pkr":0.0,"pln":0.0,"rub":0.0,"sar":0.0,"sek":0.0,"sgd":0.0,"thb":0.0,"try":0.0,"twd":0.0,"uah":0.0,"usd":0.0,"vef":0.0,"vnd":0.0,"xag":0.0,"xau":0.0,"xdr":0.0,"xlm":0.0,"xrp":0.0,"yfi":0.0,"zar":0.0,"bits":0.0,"link":0.0,"sats":0.0},"total_supply":500000000.0,"max_supply":1711136430.0,"circulating_supply":0.0,"last_updated":"2024-09-29T18:48:24.577Z"},"community_data":{"facebook_likes":null,"twitter_followers":5571,"reddit_average_posts_48h":0.0,"reddit_average_comments_48h":0.0,"reddit_subscribers":0,"reddit_accounts_active_48h":0,"telegram_channel_user_count":739},"developer_data":{"forks":0,"stars":0,"subscribers":0,"total_issues":0,"closed_issues":0,"pull_requests_merged":0,"pull_request_contributors":0,"code_additions_deletions_4_weeks":{"additions":null,"deletions":null},"commit_count_4_weeks":0,"last_4_weeks_commit_activity_series":[]},"status_updates":[],"last_updated":"2024-09-29T18:48:24.577Z","tickers":[{"base":"IBC/B1C1806A540B3E165A2D42222C59946FB85BA325596FC85662D7047649F419F3","target":"UOSMO","market":{"name":"Osmosis","identifier":"osmosis","has_trading_incentive":false},"last":0.01236002112656158,"volume":74732.89045739913,"converted_last":{"btc":1.23934e-07,"eth":3.06e-06,"usd":0.0081562},"converted_volume":{"btc":0.00926195,"eth":0.22884623,"usd":609.54},"trust_score":"yellow","bid_ask_spread_percentage":0.608983,"timestamp":"2024-09-29T18:37:22+00:00","last_traded_at":"2024-09-29T18:37:22+00:00","last_fetch_at":"2024-09-29T18:48:21+00:00","is_anomaly":false,"is_stale":false,"trade_url":"https://app.osmosis.zone/?from=ibc/B1C1806A540B3E165A2D42222C59946FB85BA325596FC85662D7047649F419F3\u0026to=uosmo","token_info_url":null,"coin_id":"gitopia","target_coin_id":"osmosis"}]}
